[
    {
        "@timestamp": "2024-11-21 02:24:17.977",
        "kubernetes.container_name": "notification-service",
        "logBody": {
            "@timestamp": "2024-11-21T02:24:17.977Z",
            "@version": "1",
            "message": "Get the notification template name UNSUCCESSFUL_ONBOARDING, for customer f66bea1f-7618-4b36-95ae-7aac367c1758",
            "logger_name": "com.arbm.digibank.service.NotificationTemplateService",
            "thread_name": "org.springframework.kafka.KafkaListenerEndpointContainer#0-0-C-1",
            "level": "INFO",
            "level_value": 20000,
            "springAppName": "notification-service",
            "traceId": "673e99d1020e79b45863dfad2e8f9fdd",
            "spanId": "e7a89898060468b0",
            "bc": "shared"
        }
    },
    {
        "@timestamp": "2024-11-21 02:21:01.397",
        "kubernetes.container_name": "notification-service",
        "logBody": {
            "@timestamp": "2024-11-21T02:21:01.397Z",
            "@version": "1",
            "message": "Get the notification template name UNSUCCESSFUL_ONBOARDING, for customer f66bea1f-7618-4b36-95ae-7aac367c1758",
            "logger_name": "com.arbm.digibank.service.NotificationTemplateService",
            "thread_name": "org.springframework.kafka.KafkaListenerEndpointContainer#0-0-C-1",
            "level": "INFO",
            "level_value": 20000,
            "springAppName": "notification-service",
            "traceId": "673e990814aaed99b973330f37c0f819",
            "spanId": "69204f289f44e393",
            "bc": "shared"
        }
    },
    {
        "@timestamp": "2024-11-21 01:42:57.179",
        "kubernetes.container_name": "notification-service",
        "logBody": {
            "@timestamp": "2024-11-21T01:42:57.179Z",
            "@version": "1",
            "message": "Get the notification template name UNSUCCESSFUL_ONBOARDING, for customer b70d627c-0d6a-489c-ad25-016d7e86e4b3",
            "logger_name": "com.arbm.digibank.service.NotificationTemplateService",
            "thread_name": "org.springframework.kafka.KafkaListenerEndpointContainer#0-0-C-1",
            "level": "INFO",
            "level_value": 20000,
            "springAppName": "notification-service",
            "traceId": "673e901c3ac8936253f3ddde381567de",
            "spanId": "38db808212d4415a",
            "bc": "shared"
        }
    },
    {
        "@timestamp": "2024-11-21 01:28:08.639",
        "kubernetes.container_name": "notification-service",
        "logBody": {
            "@timestamp": "2024-11-21T01:28:08.639Z",
            "@version": "1",
            "message": "Get the notification template name UNSUCCESSFUL_ONBOARDING, for customer eef8a2f6-aa03-4d35-b349-09e97ccd0df6",
            "logger_name": "com.arbm.digibank.service.NotificationTemplateService",
            "thread_name": "org.springframework.kafka.KafkaListenerEndpointContainer#0-0-C-1",
            "level": "INFO",
            "level_value": 20000,
            "springAppName": "notification-service",
            "traceId": "673e8c9e3d461c6e35c1b7e542ec1647",
            "spanId": "7e1b2849b831c2dc",
            "bc": "shared"
        }
    },
    {
        "@timestamp": "2024-11-21 00:34:31.231",
        "kubernetes.container_name": "notification-service",
        "logBody": {
            "@timestamp": "2024-11-21T00:34:31.231Z",
            "@version": "1",
            "message": "Get the notification template name UNSUCCESSFUL_ONBOARDING, for customer bcdbc01e-ce87-4cfa-b0a9-cfd0a67afb97",
            "logger_name": "com.arbm.digibank.service.NotificationTemplateService",
            "thread_name": "org.springframework.kafka.KafkaListenerEndpointContainer#0-0-C-1",
            "level": "INFO",
            "level_value": 20000,
            "springAppName": "notification-service",
            "traceId": "673e8012d98781a65357c7e66fa4b0f3",
            "spanId": "9e061585faa74d74",
            "bc": "shared"
        }
    },
    {
        "@timestamp": "2024-11-20 20:17:51.603",
        "kubernetes.container_name": "notification-service",
        "logBody": {
            "@timestamp": "2024-11-20T20:17:51.555Z",
            "@version": "1",
            "message": "Get the notification template name UNSUCCESSFUL_ONBOARDING, for customer ee2b92da-34d8-4016-a513-4c1a3a73f733",
            "logger_name": "com.arbm.digibank.service.NotificationTemplateService",
            "thread_name": "org.springframework.kafka.KafkaListenerEndpointContainer#0-0-C-1",
            "level": "INFO",
            "level_value": 20000,
            "springAppName": "notification-service",
            "traceId": "673e43e96ee84934f122ff9b25bdd86d",
            "spanId": "3c3278ff52446e4e",
            "bc": "shared"
        }
    },
    {
        "@timestamp": "2024-11-20 16:52:56.181",
        "kubernetes.container_name": "notification-service",
        "logBody": {
            "@timestamp": "2024-11-20T16:52:56.181Z",
            "@version": "1",
            "message": "Get the notification template name UNSUCCESSFUL_ONBOARDING, for customer d587cea8-b7fc-48bd-8cc4-5a0c06cb484e",
            "logger_name": "com.arbm.digibank.service.NotificationTemplateService",
            "thread_name": "org.springframework.kafka.KafkaListenerEndpointContainer#0-0-C-1",
            "level": "INFO",
            "level_value": 20000,
            "springAppName": "notification-service",
            "traceId": "673e13e0adbca0ead547905e442d4b02",
            "spanId": "8179ca7baa8abb13",
            "bc": "shared"
        }
    },
    {
        "@timestamp": "2024-11-20 14:22:20.025",
        "kubernetes.container_name": "notification-service",
        "logBody": {
            "@timestamp": "2024-11-20T14:22:20.025Z",
            "@version": "1",
            "message": "Get the notification template name UNSUCCESSFUL_ONBOARDING, for customer bd62761c-e410-4b95-a4c3-3e6c2b1849ea",
            "logger_name": "com.arbm.digibank.service.NotificationTemplateService",
            "thread_name": "org.springframework.kafka.KafkaListenerEndpointContainer#0-0-C-1",
            "level": "INFO",
            "level_value": 20000,
            "springAppName": "notification-service",
            "traceId": "673df095fa82ce3b48f4272d91b145d9",
            "spanId": "a0c463465283fe72",
            "bc": "shared"
        }
    },
    {
        "@timestamp": "2024-11-20 12:39:15.870",
        "kubernetes.container_name": "notification-service",
        "logBody": {
            "@timestamp": "2024-11-20T12:39:15.87Z",
            "@version": "1",
            "message": "Get the notification template name UNSUCCESSFUL_ONBOARDING, for customer 58e628f8-dc99-43a7-ac86-4267cfbb3c93",
            "logger_name": "com.arbm.digibank.service.NotificationTemplateService",
            "thread_name": "org.springframework.kafka.KafkaListenerEndpointContainer#0-0-C-1",
            "level": "INFO",
            "level_value": 20000,
            "springAppName": "notification-service",
            "traceId": "673dd8736cda41bd99e68a9a9c20a702",
            "spanId": "1a60c20b65b25756",
            "bc": "shared"
        }
    },
    {
        "@timestamp": "2024-11-20 12:36:00.484",
        "kubernetes.container_name": "notification-service",
        "logBody": {
            "@timestamp": "2024-11-20T12:36:00.484Z",
            "@version": "1",
            "message": "Get the notification template name UNSUCCESSFUL_ONBOARDING, for customer 58e628f8-dc99-43a7-ac86-4267cfbb3c93",
            "logger_name": "com.arbm.digibank.service.NotificationTemplateService",
            "thread_name": "org.springframework.kafka.KafkaListenerEndpointContainer#0-0-C-1",
            "level": "INFO",
            "level_value": 20000,
            "springAppName": "notification-service",
            "traceId": "673dd7addb062899221cd129252c38d1",
            "spanId": "3b6b83e389e9ea16",
            "bc": "shared"
        }
    },
    {
        "@timestamp": "2024-11-20 11:41:04.203",
        "kubernetes.container_name": "notification-service",
        "logBody": {
            "@timestamp": "2024-11-20T11:41:04.203Z",
            "@version": "1",
            "message": "Get the notification template name UNSUCCESSFUL_ONBOARDING, for customer 4cdc5d8a-319a-4b2d-8e65-82f2686252bb",
            "logger_name": "com.arbm.digibank.service.NotificationTemplateService",
            "thread_name": "org.springframework.kafka.KafkaListenerEndpointContainer#0-0-C-1",
            "level": "INFO",
            "level_value": 20000,
            "springAppName": "notification-service",
            "traceId": "673dcacb3a366105a5f5d7555161eaf2",
            "spanId": "8b51e1938d505ef8",
            "bc": "shared"
        }
    },
    {
        "@timestamp": "2024-11-20 11:13:28.587",
        "kubernetes.container_name": "notification-service",
        "logBody": {
            "@timestamp": "2024-11-20T11:13:28.587Z",
            "@version": "1",
            "message": "Get the notification template name UNSUCCESSFUL_ONBOARDING, for customer 978c0aab-b51a-487c-b78d-719cf84660bd",
            "logger_name": "com.arbm.digibank.service.NotificationTemplateService",
            "thread_name": "org.springframework.kafka.KafkaListenerEndpointContainer#0-0-C-1",
            "level": "INFO",
            "level_value": 20000,
            "springAppName": "notification-service",
            "traceId": "673dc456bfd7c87c8fd6aa4e775aaada",
            "spanId": "3ae5ee806cb55f8f",
            "bc": "shared"
        }
    },
    {
        "@timestamp": "2024-11-20 10:51:16.771",
        "kubernetes.container_name": "notification-service",
        "logBody": {
            "@timestamp": "2024-11-20T10:51:16.694Z",
            "@version": "1",
            "message": "Get the notification template name UNSUCCESSFUL_ONBOARDING, for customer 50a173bd-e052-4887-93cb-ac78f97286aa",
            "logger_name": "com.arbm.digibank.service.NotificationTemplateService",
            "thread_name": "org.springframework.kafka.KafkaListenerEndpointContainer#0-0-C-1",
            "level": "INFO",
            "level_value": 20000,
            "springAppName": "notification-service",
            "traceId": "673dbf240f31c74160c6a75e459fcdf5",
            "spanId": "9053d7dc7eade50c",
            "bc": "shared"
        }
    },
    {
        "@timestamp": "2024-11-20 10:47:44.795",
        "kubernetes.container_name": "notification-service",
        "logBody": {
            "@timestamp": "2024-11-20T10:47:44.795Z",
            "@version": "1",
            "message": "Get the notification template name UNSUCCESSFUL_ONBOARDING, for customer 50a173bd-e052-4887-93cb-ac78f97286aa",
            "logger_name": "com.arbm.digibank.service.NotificationTemplateService",
            "thread_name": "org.springframework.kafka.KafkaListenerEndpointContainer#0-0-C-1",
            "level": "INFO",
            "level_value": 20000,
            "springAppName": "notification-service",
            "traceId": "673dbe508f644c70436eea6ee058f758",
            "spanId": "ec3ae08d23b695df",
            "bc": "shared"
        }
    },
    {
        "@timestamp": "2024-11-20 10:44:07.218",
        "kubernetes.container_name": "notification-service",
        "logBody": {
            "@timestamp": "2024-11-20T10:44:07.218Z",
            "@version": "1",
            "message": "Get the notification template name UNSUCCESSFUL_ONBOARDING, for customer bba61210-ed0c-4db9-8029-bca4fd61c4a0",
            "logger_name": "com.arbm.digibank.service.NotificationTemplateService",
            "thread_name": "org.springframework.kafka.KafkaListenerEndpointContainer#0-0-C-1",
            "level": "INFO",
            "level_value": 20000,
            "springAppName": "notification-service",
            "traceId": "673dbd6f01c40cf9f50dfc71f8aac09f",
            "spanId": "9b07547e1bf6ec97",
            "bc": "shared"
        }
    },
    {
        "@timestamp": "2024-11-20 09:15:07.484",
        "kubernetes.container_name": "notification-service",
        "logBody": {
            "@timestamp": "2024-11-20T09:15:07.483Z",
            "@version": "1",
            "message": "Get the notification template name UNSUCCESSFUL_ONBOARDING, for customer 96fd9a3a-c286-4025-90fa-9d10dfc9a043",
            "logger_name": "com.arbm.digibank.service.NotificationTemplateService",
            "thread_name": "org.springframework.kafka.KafkaListenerEndpointContainer#0-0-C-1",
            "level": "INFO",
            "level_value": 20000,
            "springAppName": "notification-service",
            "traceId": "673da89bafadcd09711eef5d3c55614d",
            "spanId": "154892264b29653a",
            "bc": "shared"
        }
    },
    {
        "@timestamp": "2024-11-20 09:12:46.184",
        "kubernetes.container_name": "notification-service",
        "logBody": {
            "@timestamp": "2024-11-20T09:12:46.184Z",
            "@version": "1",
            "message": "Get the notification template name UNSUCCESSFUL_ONBOARDING, for customer 96fd9a3a-c286-4025-90fa-9d10dfc9a043",
            "logger_name": "com.arbm.digibank.service.NotificationTemplateService",
            "thread_name": "org.springframework.kafka.KafkaListenerEndpointContainer#0-0-C-1",
            "level": "INFO",
            "level_value": 20000,
            "springAppName": "notification-service",
            "traceId": "673da80aa2fcdebf0f78a4485c077c55",
            "spanId": "8d7568b337cd5309",
            "bc": "shared"
        }
    },
    {
        "@timestamp": "2024-11-20 01:48:57.132",
        "kubernetes.container_name": "notification-service",
        "logBody": {
            "@timestamp": "2024-11-20T01:48:57.132Z",
            "@version": "1",
            "message": "Get the notification template name UNSUCCESSFUL_ONBOARDING, for customer 1ce8a02e-f511-468c-99f6-783d75b0dd57",
            "logger_name": "com.arbm.digibank.service.NotificationTemplateService",
            "thread_name": "org.springframework.kafka.KafkaListenerEndpointContainer#0-0-C-1",
            "level": "INFO",
            "level_value": 20000,
            "springAppName": "notification-service",
            "traceId": "673d4003275913bf3ce8906a5659e2fe",
            "spanId": "8461d273e18c0632",
            "bc": "shared"
        }
    },
    {
        "@timestamp": "2024-11-20 01:24:42.047",
        "kubernetes.container_name": "notification-service",
        "logBody": {
            "@timestamp": "2024-11-20T01:24:42.047Z",
            "@version": "1",
            "message": "Get the notification template name UNSUCCESSFUL_ONBOARDING, for customer 0773ead4-3e87-4ab6-a3c7-b18ea3e2522e",
            "logger_name": "com.arbm.digibank.service.NotificationTemplateService",
            "thread_name": "org.springframework.kafka.KafkaListenerEndpointContainer#0-0-C-1",
            "level": "INFO",
            "level_value": 20000,
            "springAppName": "notification-service",
            "traceId": "673d3a51557a0096306d7a7229df3382",
            "spanId": "cc51ae0effe14906",
            "bc": "shared"
        }
    },
    {
        "@timestamp": "2024-11-19 23:21:41.214",
        "kubernetes.container_name": "notification-service",
        "logBody": {
            "@timestamp": "2024-11-19T23:21:41.214Z",
            "@version": "1",
            "message": "Get the notification template name UNSUCCESSFUL_ONBOARDING, for customer 57e684a4-e2d0-46c3-a72e-0186ecf70034",
            "logger_name": "com.arbm.digibank.service.NotificationTemplateService",
            "thread_name": "org.springframework.kafka.KafkaListenerEndpointContainer#0-0-C-1",
            "level": "INFO",
            "level_value": 20000,
            "springAppName": "notification-service",
            "traceId": "673d1d7d54418befffa3ffd55127b758",
            "spanId": "e1fc5e159628ae87",
            "bc": "shared"
        }
    },
    {
        "@timestamp": "2024-11-19 15:01:39.631",
        "kubernetes.container_name": "notification-service",
        "logBody": {
            "@timestamp": "2024-11-19T15:01:39.631Z",
            "@version": "1",
            "message": "Get the notification template name UNSUCCESSFUL_ONBOARDING, for customer 735f2978-1dc9-499a-b745-14cfddaffc41",
            "logger_name": "com.arbm.digibank.service.NotificationTemplateService",
            "thread_name": "org.springframework.kafka.KafkaListenerEndpointContainer#0-0-C-1",
            "level": "INFO",
            "level_value": 20000,
            "springAppName": "notification-service",
            "traceId": "673ca8491614643d286b227f59aed915",
            "spanId": "ed65d1757373c11f",
            "bc": "shared"
        }
    },
    {
        "@timestamp": "2024-11-19 15:01:39.597",
        "kubernetes.container_name": "notification-service",
        "logBody": {
            "@timestamp": "2024-11-19T15:01:39.58Z",
            "@version": "1",
            "message": "Get the notification template name UNSUCCESSFUL_ONBOARDING, for customer 735f2978-1dc9-499a-b745-14cfddaffc41",
            "logger_name": "com.arbm.digibank.service.NotificationTemplateService",
            "thread_name": "org.springframework.kafka.KafkaListenerEndpointContainer#0-0-C-1",
            "level": "INFO",
            "level_value": 20000,
            "springAppName": "notification-service",
            "traceId": "673ca8491614643d286b227f59aed915",
            "spanId": "0c3b7f962c1237ad",
            "bc": "shared"
        }
    },
    {
        "@timestamp": "2024-11-19 15:01:39.528",
        "kubernetes.container_name": "notification-service",
        "logBody": {
            "@timestamp": "2024-11-19T15:01:39.528Z",
            "@version": "1",
            "message": "Get the notification template name UNSUCCESSFUL_ONBOARDING, for customer 735f2978-1dc9-499a-b745-14cfddaffc41",
            "logger_name": "com.arbm.digibank.service.NotificationTemplateService",
            "thread_name": "org.springframework.kafka.KafkaListenerEndpointContainer#0-0-C-1",
            "level": "INFO",
            "level_value": 20000,
            "springAppName": "notification-service",
            "traceId": "673ca8491614643d286b227f59aed915",
            "spanId": "1609871bdc471461",
            "bc": "shared"
        }
    },
    {
        "@timestamp": "2024-11-19 15:01:39.467",
        "kubernetes.container_name": "notification-service",
        "logBody": {
            "@timestamp": "2024-11-19T15:01:39.467Z",
            "@version": "1",
            "message": "Get the notification template name UNSUCCESSFUL_ONBOARDING, for customer 735f2978-1dc9-499a-b745-14cfddaffc41",
            "logger_name": "com.arbm.digibank.service.NotificationTemplateService",
            "thread_name": "org.springframework.kafka.KafkaListenerEndpointContainer#0-0-C-1",
            "level": "INFO",
            "level_value": 20000,
            "springAppName": "notification-service",
            "traceId": "673ca8491614643d286b227f59aed915",
            "spanId": "86d303d2fa329b14",
            "bc": "shared"
        }
    },
    {
        "@timestamp": "2024-11-19 15:01:37.119",
        "kubernetes.container_name": "notification-service",
        "logBody": {
            "@timestamp": "2024-11-19T15:01:37.119Z",
            "@version": "1",
            "message": "Get the notification template name UNSUCCESSFUL_ONBOARDING, for customer 735f2978-1dc9-499a-b745-14cfddaffc41",
            "logger_name": "com.arbm.digibank.service.NotificationTemplateService",
            "thread_name": "org.springframework.kafka.KafkaListenerEndpointContainer#0-0-C-1",
            "level": "INFO",
            "level_value": 20000,
            "springAppName": "notification-service",
            "traceId": "673ca8491614643d286b227f59aed915",
            "spanId": "022383dc5130ebe7",
            "bc": "shared"
        }
    },
    {
        "@timestamp": "2024-11-19 13:04:04.647",
        "kubernetes.container_name": "notification-service",
        "logBody": {
            "@timestamp": "2024-11-19T13:04:04.576Z",
            "@version": "1",
            "message": "Get the notification template name UNSUCCESSFUL_ONBOARDING, for customer 2dda7c47-3fcc-42fa-a1a9-b1b9c3965cb3",
            "logger_name": "com.arbm.digibank.service.NotificationTemplateService",
            "thread_name": "org.springframework.kafka.KafkaListenerEndpointContainer#0-0-C-1",
            "level": "INFO",
            "level_value": 20000,
            "springAppName": "notification-service",
            "traceId": "673c8cc4d7a60e289ff5d86ed89403af",
            "spanId": "8ada77b31745a117",
            "bc": "shared"
        }
    },
    {
        "@timestamp": "2024-11-19 12:59:03.699",
        "kubernetes.container_name": "notification-service",
        "logBody": {
            "@timestamp": "2024-11-19T12:59:03.699Z",
            "@version": "1",
            "message": "Get the notification template name UNSUCCESSFUL_ONBOARDING, for customer 3349119c-d8df-4528-900d-5a66ef0aefd2",
            "logger_name": "com.arbm.digibank.service.NotificationTemplateService",
            "thread_name": "org.springframework.kafka.KafkaListenerEndpointContainer#0-0-C-1",
            "level": "INFO",
            "level_value": 20000,
            "springAppName": "notification-service",
            "traceId": "673c8b97a7f4b8b4f320e5e2ea223dd1",
            "spanId": "8ae9fa22dda3d8e5",
            "bc": "shared"
        }
    },
    {
        "@timestamp": "2024-11-19 12:55:19.946",
        "kubernetes.container_name": "notification-service",
        "logBody": {
            "@timestamp": "2024-11-19T12:55:19.946Z",
            "@version": "1",
            "message": "Get the notification template name UNSUCCESSFUL_ONBOARDING, for customer 0773ead4-3e87-4ab6-a3c7-b18ea3e2522e",
            "logger_name": "com.arbm.digibank.service.NotificationTemplateService",
            "thread_name": "org.springframework.kafka.KafkaListenerEndpointContainer#0-0-C-1",
            "level": "INFO",
            "level_value": 20000,
            "springAppName": "notification-service",
            "traceId": "673c8ab73d216cc774b321ed194e5a57",
            "spanId": "c350f9ee53e8e775",
            "bc": "shared"
        }
    },
    {
        "@timestamp": "2024-11-19 12:54:20.092",
        "kubernetes.container_name": "notification-service",
        "logBody": {
            "@timestamp": "2024-11-19T12:54:20.092Z",
            "@version": "1",
            "message": "Get the notification template name UNSUCCESSFUL_ONBOARDING, for customer 2dda7c47-3fcc-42fa-a1a9-b1b9c3965cb3",
            "logger_name": "com.arbm.digibank.service.NotificationTemplateService",
            "thread_name": "org.springframework.kafka.KafkaListenerEndpointContainer#0-0-C-1",
            "level": "INFO",
            "level_value": 20000,
            "springAppName": "notification-service",
            "traceId": "673c8a77df4812702514c9f6599fbce4",
            "spanId": "37596d5e47f05183",
            "bc": "shared"
        }
    },
    {
        "@timestamp": "2024-11-19 12:27:08.014",
        "kubernetes.container_name": "notification-service",
        "logBody": {
            "@timestamp": "2024-11-19T12:27:08.014Z",
            "@version": "1",
            "message": "Get the notification template name UNSUCCESSFUL_ONBOARDING, for customer 31a77c59-7ac4-451f-90c9-58643d67f51c",
            "logger_name": "com.arbm.digibank.service.NotificationTemplateService",
            "thread_name": "org.springframework.kafka.KafkaListenerEndpointContainer#0-0-C-1",
            "level": "INFO",
            "level_value": 20000,
            "springAppName": "notification-service",
            "traceId": "673c8416193e96a9c5b341ebed534381",
            "spanId": "367e316e8455e7a2",
            "bc": "shared"
        }
    },
    {
        "@timestamp": "2024-11-19 10:22:04.652",
        "kubernetes.container_name": "notification-service",
        "logBody": {
            "@timestamp": "2024-11-19T10:22:04.57Z",
            "@version": "1",
            "message": "Get the notification template name UNSUCCESSFUL_ONBOARDING, for customer a093b285-efeb-4348-a1fd-fb773c4ec08f",
            "logger_name": "com.arbm.digibank.service.NotificationTemplateService",
            "thread_name": "org.springframework.kafka.KafkaListenerEndpointContainer#0-0-C-1",
            "level": "INFO",
            "level_value": 20000,
            "springAppName": "notification-service",
            "traceId": "673c66cc1e57de5f1ec6405ccd99b537",
            "spanId": "43dc7e24a7f40b3d",
            "bc": "shared"
        }
    },
    {
        "@timestamp": "2024-11-19 10:20:44.617",
        "kubernetes.container_name": "notification-service",
        "logBody": {
            "@timestamp": "2024-11-19T10:20:44.565Z",
            "@version": "1",
            "message": "Get the notification template name UNSUCCESSFUL_ONBOARDING, for customer a093b285-efeb-4348-a1fd-fb773c4ec08f",
            "logger_name": "com.arbm.digibank.service.NotificationTemplateService",
            "thread_name": "org.springframework.kafka.KafkaListenerEndpointContainer#0-0-C-1",
            "level": "INFO",
            "level_value": 20000,
            "springAppName": "notification-service",
            "traceId": "673c6677d9c565f31b3fe8d4a2972276",
            "spanId": "4a6189a60c9958a5",
            "bc": "shared"
        }
    },
    {
        "@timestamp": "2024-11-19 06:32:14.552",
        "kubernetes.container_name": "notification-service",
        "logBody": {
            "@timestamp": "2024-11-19T06:32:14.544Z",
            "@version": "1",
            "message": "Get the notification template name UNSUCCESSFUL_ONBOARDING, for customer 7142e27d-20f8-473c-8d2b-cbf3bfa05c58",
            "logger_name": "com.arbm.digibank.service.NotificationTemplateService",
            "thread_name": "org.springframework.kafka.KafkaListenerEndpointContainer#0-0-C-1",
            "level": "INFO",
            "level_value": 20000,
            "springAppName": "notification-service",
            "traceId": "673c30e43d51eb643c06c3272fefec87",
            "spanId": "abd3bb472b480fea",
            "bc": "shared"
        }
    },
    {
        "@timestamp": "2024-11-19 05:53:23.737",
        "kubernetes.container_name": "notification-service",
        "logBody": {
            "@timestamp": "2024-11-19T05:53:23.736Z",
            "@version": "1",
            "message": "Get the notification template name UNSUCCESSFUL_ONBOARDING, for customer e7d8d74e-e374-450e-991c-9877e8f9151a",
            "logger_name": "com.arbm.digibank.service.NotificationTemplateService",
            "thread_name": "org.springframework.kafka.KafkaListenerEndpointContainer#0-0-C-1",
            "level": "INFO",
            "level_value": 20000,
            "springAppName": "notification-service",
            "traceId": "673c27d1be1a777c729794afa51e45e5",
            "spanId": "34d53759bcf8d4cb",
            "bc": "shared"
        }
    },
    {
        "@timestamp": "2024-11-19 05:43:02.683",
        "kubernetes.container_name": "notification-service",
        "logBody": {
            "@timestamp": "2024-11-19T05:43:02.683Z",
            "@version": "1",
            "message": "Get the notification template name UNSUCCESSFUL_ONBOARDING, for customer e7d8d74e-e374-450e-991c-9877e8f9151a",
            "logger_name": "com.arbm.digibank.service.NotificationTemplateService",
            "thread_name": "org.springframework.kafka.KafkaListenerEndpointContainer#0-0-C-1",
            "level": "INFO",
            "level_value": 20000,
            "springAppName": "notification-service",
            "traceId": "673c255f60590cc19129b224f7491fb0",
            "spanId": "f4e6a9a15de38f66",
            "bc": "shared"
        }
    },
    {
        "@timestamp": "2024-11-19 05:39:12.527",
        "kubernetes.container_name": "notification-service",
        "logBody": {
            "@timestamp": "2024-11-19T05:39:12.526Z",
            "@version": "1",
            "message": "Get the notification template name UNSUCCESSFUL_ONBOARDING, for customer 81a3554b-c57e-4ef1-89da-a02c73772b59",
            "logger_name": "com.arbm.digibank.service.NotificationTemplateService",
            "thread_name": "org.springframework.kafka.KafkaListenerEndpointContainer#0-0-C-1",
            "level": "INFO",
            "level_value": 20000,
            "springAppName": "notification-service",
            "traceId": "673c247b1d0f0d4d1df86f4a10c0f12e",
            "spanId": "7d326951ae0a5298",
            "bc": "shared"
        }
    },
    {
        "@timestamp": "2024-11-19 05:39:12.477",
        "kubernetes.container_name": "notification-service",
        "logBody": {
            "@timestamp": "2024-11-19T05:39:12.477Z",
            "@version": "1",
            "message": "Get the notification template name UNSUCCESSFUL_ONBOARDING, for customer 81a3554b-c57e-4ef1-89da-a02c73772b59",
            "logger_name": "com.arbm.digibank.service.NotificationTemplateService",
            "thread_name": "org.springframework.kafka.KafkaListenerEndpointContainer#0-0-C-1",
            "level": "INFO",
            "level_value": 20000,
            "springAppName": "notification-service",
            "traceId": "673c247b1d0f0d4d1df86f4a10c0f12e",
            "spanId": "cd9583bfdbf47bde",
            "bc": "shared"
        }
    },
    {
        "@timestamp": "2024-11-19 05:39:12.430",
        "kubernetes.container_name": "notification-service",
        "logBody": {
            "@timestamp": "2024-11-19T05:39:12.43Z",
            "@version": "1",
            "message": "Get the notification template name UNSUCCESSFUL_ONBOARDING, for customer 81a3554b-c57e-4ef1-89da-a02c73772b59",
            "logger_name": "com.arbm.digibank.service.NotificationTemplateService",
            "thread_name": "org.springframework.kafka.KafkaListenerEndpointContainer#0-0-C-1",
            "level": "INFO",
            "level_value": 20000,
            "springAppName": "notification-service",
            "traceId": "673c247b1d0f0d4d1df86f4a10c0f12e",
            "spanId": "8f2ff1fc216ae87a",
            "bc": "shared"
        }
    },
    {
        "@timestamp": "2024-11-19 05:39:12.365",
        "kubernetes.container_name": "notification-service",
        "logBody": {
            "@timestamp": "2024-11-19T05:39:12.364Z",
            "@version": "1",
            "message": "Get the notification template name UNSUCCESSFUL_ONBOARDING, for customer 81a3554b-c57e-4ef1-89da-a02c73772b59",
            "logger_name": "com.arbm.digibank.service.NotificationTemplateService",
            "thread_name": "org.springframework.kafka.KafkaListenerEndpointContainer#0-0-C-1",
            "level": "INFO",
            "level_value": 20000,
            "springAppName": "notification-service",
            "traceId": "673c247b1d0f0d4d1df86f4a10c0f12e",
            "spanId": "9e75190d65e8bbd4",
            "bc": "shared"
        }
    },
    {
        "@timestamp": "2024-11-19 05:39:09.229",
        "kubernetes.container_name": "notification-service",
        "logBody": {
            "@timestamp": "2024-11-19T05:39:09.229Z",
            "@version": "1",
            "message": "Get the notification template name UNSUCCESSFUL_ONBOARDING, for customer 81a3554b-c57e-4ef1-89da-a02c73772b59",
            "logger_name": "com.arbm.digibank.service.NotificationTemplateService",
            "thread_name": "org.springframework.kafka.KafkaListenerEndpointContainer#0-0-C-1",
            "level": "INFO",
            "level_value": 20000,
            "springAppName": "notification-service",
            "traceId": "673c247b1d0f0d4d1df86f4a10c0f12e",
            "spanId": "5de77d7dfe17c1a4",
            "bc": "shared"
        }
    },
    {
        "@timestamp": "2024-11-19 03:01:33.917",
        "kubernetes.container_name": "notification-service",
        "logBody": {
            "@timestamp": "2024-11-19T03:01:33.917Z",
            "@version": "1",
            "message": "Get the notification template name UNSUCCESSFUL_ONBOARDING, for customer 9b431493-33b1-40e8-823f-5a0caddb1d0b",
            "logger_name": "com.arbm.digibank.service.NotificationTemplateService",
            "thread_name": "org.springframework.kafka.KafkaListenerEndpointContainer#0-0-C-1",
            "level": "INFO",
            "level_value": 20000,
            "springAppName": "notification-service",
            "traceId": "673bff89194d3a78e40b01af326d0ff9",
            "spanId": "8e4712a1695fa5a5",
            "bc": "shared"
        }
    },
    {
        "@timestamp": "2024-11-19 02:41:10.657",
        "kubernetes.container_name": "notification-service",
        "logBody": {
            "@timestamp": "2024-11-19T02:41:10.657Z",
            "@version": "1",
            "message": "Get the notification template name UNSUCCESSFUL_ONBOARDING, for customer 1731983769005233",
            "logger_name": "com.arbm.digibank.service.NotificationTemplateService",
            "thread_name": "org.springframework.kafka.KafkaListenerEndpointContainer#0-0-C-1",
            "level": "INFO",
            "level_value": 20000,
            "springAppName": "notification-service",
            "traceId": "673bfabf071afe30ffb5e7f87308241e",
            "spanId": "f8cbe2eb934b49b7",
            "bc": "shared"
        }
    },
    {
        "@timestamp": "2024-11-19 02:04:44.368",
        "kubernetes.container_name": "notification-service",
        "logBody": {
            "@timestamp": "2024-11-19T02:04:44.367Z",
            "@version": "1",
            "message": "Get the notification template name UNSUCCESSFUL_ONBOARDING, for customer 095f9912-9c45-4493-ba2a-b93de5da18bc",
            "logger_name": "com.arbm.digibank.service.NotificationTemplateService",
            "thread_name": "org.springframework.kafka.KafkaListenerEndpointContainer#0-0-C-1",
            "level": "INFO",
            "level_value": 20000,
            "springAppName": "notification-service",
            "traceId": "673bf23cb5ceafaed367a4f27cf95334",
            "spanId": "b90e11738cdfacfe",
            "bc": "shared"
        }
    },
    {
        "@timestamp": "2024-11-19 02:02:21.947",
        "kubernetes.container_name": "notification-service",
        "logBody": {
            "@timestamp": "2024-11-19T02:02:21.947Z",
            "@version": "1",
            "message": "Get the notification template name UNSUCCESSFUL_ONBOARDING, for customer 33331f0c-bc0e-4842-9a97-0bc6b82cdd7e",
            "logger_name": "com.arbm.digibank.service.NotificationTemplateService",
            "thread_name": "org.springframework.kafka.KafkaListenerEndpointContainer#0-0-C-1",
            "level": "INFO",
            "level_value": 20000,
            "springAppName": "notification-service",
            "traceId": "673bf1adc75a942a1aee31984e82f482",
            "spanId": "bdb1811a993c5ff5",
            "bc": "shared"
        }
    },
    {
        "@timestamp": "2024-11-19 01:59:29.685",
        "kubernetes.container_name": "notification-service",
        "logBody": {
            "@timestamp": "2024-11-19T01:59:29.685Z",
            "@version": "1",
            "message": "Get the notification template name UNSUCCESSFUL_ONBOARDING, for customer 095f9912-9c45-4493-ba2a-b93de5da18bc",
            "logger_name": "com.arbm.digibank.service.NotificationTemplateService",
            "thread_name": "org.springframework.kafka.KafkaListenerEndpointContainer#0-0-C-1",
            "level": "INFO",
            "level_value": 20000,
            "springAppName": "notification-service",
            "traceId": "673bf0fe64bf076738a4664021f8596e",
            "spanId": "c08fdb6d7788cf97",
            "bc": "shared"
        }
    },
    {
        "@timestamp": "2024-11-19 01:39:02.186",
        "kubernetes.container_name": "notification-service",
        "logBody": {
            "@timestamp": "2024-11-19T01:39:02.186Z",
            "@version": "1",
            "message": "Get the notification template name UNSUCCESSFUL_ONBOARDING, for customer 4ac03dbf-d4d4-4307-a62c-f0522b916a62",
            "logger_name": "com.arbm.digibank.service.NotificationTemplateService",
            "thread_name": "org.springframework.kafka.KafkaListenerEndpointContainer#0-0-C-1",
            "level": "INFO",
            "level_value": 20000,
            "springAppName": "notification-service",
            "traceId": "673bec30a9de48462d586769671ebafa",
            "spanId": "b8058d07ebbe4a24",
            "bc": "shared"
        }
    },
    {
        "@timestamp": "2024-11-18 13:33:50.725",
        "kubernetes.container_name": "notification-service",
        "logBody": {
            "@timestamp": "2024-11-18T13:33:50.725Z",
            "@version": "1",
            "message": "Get the notification template name UNSUCCESSFUL_ONBOARDING, for customer e376f8e3-6dc4-4968-b427-ac1af517f3e0",
            "logger_name": "com.arbm.digibank.service.NotificationTemplateService",
            "thread_name": "org.springframework.kafka.KafkaListenerEndpointContainer#0-0-C-1",
            "level": "INFO",
            "level_value": 20000,
            "springAppName": "notification-service",
            "traceId": "673b423e18c75e8a251e9e0c0045ab01",
            "spanId": "aec2b9a0c880028e",
            "bc": "shared"
        }
    },
    {
        "@timestamp": "2024-11-18 13:32:26.523",
        "kubernetes.container_name": "notification-service",
        "logBody": {
            "@timestamp": "2024-11-18T13:32:26.523Z",
            "@version": "1",
            "message": "Get the notification template name UNSUCCESSFUL_ONBOARDING, for customer e376f8e3-6dc4-4968-b427-ac1af517f3e0",
            "logger_name": "com.arbm.digibank.service.NotificationTemplateService",
            "thread_name": "org.springframework.kafka.KafkaListenerEndpointContainer#0-0-C-1",
            "level": "INFO",
            "level_value": 20000,
            "springAppName": "notification-service",
            "traceId": "673b41e3e5a031e8ed9b052335ed1f13",
            "spanId": "f4698f0893968509",
            "bc": "shared"
        }
    },
    {
        "@timestamp": "2024-11-18 09:06:15.904",
        "kubernetes.container_name": "notification-service",
        "logBody": {
            "@timestamp": "2024-11-18T09:06:15.904Z",
            "@version": "1",
            "message": "Get the notification template name UNSUCCESSFUL_ONBOARDING, for customer 36fc1fa5-e15b-4885-98b5-e0bd7568598d",
            "logger_name": "com.arbm.digibank.service.NotificationTemplateService",
            "thread_name": "org.springframework.kafka.KafkaListenerEndpointContainer#0-0-C-1",
            "level": "INFO",
            "level_value": 20000,
            "springAppName": "notification-service",
            "traceId": "673b037e54918c743d7ff8330d2ef730",
            "spanId": "23f63ce89bd6e6d4",
            "bc": "shared"
        }
    },
    {
        "@timestamp": "2024-11-18 04:27:56.275",
        "kubernetes.container_name": "notification-service",
        "logBody": {
            "@timestamp": "2024-11-18T04:27:56.275Z",
            "@version": "1",
            "message": "Get the notification template name UNSUCCESSFUL_ONBOARDING, for customer 61856687-8a0b-4874-a6fc-355c2a34e882",
            "logger_name": "com.arbm.digibank.service.NotificationTemplateService",
            "thread_name": "org.springframework.kafka.KafkaListenerEndpointContainer#0-0-C-1",
            "level": "INFO",
            "level_value": 20000,
            "springAppName": "notification-service",
            "traceId": "673ac24c9ad2614294d810847072f16d",
            "spanId": "ecd4462a58227922",
            "bc": "shared"
        }
    },
    {
        "@timestamp": "2024-11-18 04:23:45.141",
        "kubernetes.container_name": "notification-service",
        "logBody": {
            "@timestamp": "2024-11-18T04:23:45.14Z",
            "@version": "1",
            "message": "Get the notification template name UNSUCCESSFUL_ONBOARDING, for customer 61856687-8a0b-4874-a6fc-355c2a34e882",
            "logger_name": "com.arbm.digibank.service.NotificationTemplateService",
            "thread_name": "org.springframework.kafka.KafkaListenerEndpointContainer#0-0-C-1",
            "level": "INFO",
            "level_value": 20000,
            "springAppName": "notification-service",
            "traceId": "673ac14928767ad652ea26be81bf00e5",
            "spanId": "f1b20f853d704f43",
            "bc": "shared"
        }
    },
    {
        "@timestamp": "2024-11-18 04:21:20.693",
        "kubernetes.container_name": "notification-service",
        "logBody": {
            "@timestamp": "2024-11-18T04:21:20.693Z",
            "@version": "1",
            "message": "Get the notification template name UNSUCCESSFUL_ONBOARDING, for customer 68832d05-45d6-4bc8-8e93-2d0865c26413",
            "logger_name": "com.arbm.digibank.service.NotificationTemplateService",
            "thread_name": "org.springframework.kafka.KafkaListenerEndpointContainer#0-0-C-1",
            "level": "INFO",
            "level_value": 20000,
            "springAppName": "notification-service",
            "traceId": "673ac0c0da01e7b01092abe58c169c96",
            "spanId": "15f6b9d7fd980a09",
            "bc": "shared"
        }
    },
    {
        "@timestamp": "2024-11-18 04:20:33.984",
        "kubernetes.container_name": "notification-service",
        "logBody": {
            "@timestamp": "2024-11-18T04:20:33.984Z",
            "@version": "1",
            "message": "Get the notification template name UNSUCCESSFUL_ONBOARDING, for customer 61856687-8a0b-4874-a6fc-355c2a34e882",
            "logger_name": "com.arbm.digibank.service.NotificationTemplateService",
            "thread_name": "org.springframework.kafka.KafkaListenerEndpointContainer#0-0-C-1",
            "level": "INFO",
            "level_value": 20000,
            "springAppName": "notification-service",
            "traceId": "673ac091f18dfe3f7fd8f8d1f3f6d70e",
            "spanId": "c6b4db9b400683e6",
            "bc": "shared"
        }
    },
    {
        "@timestamp": "2024-11-18 04:09:08.937",
        "kubernetes.container_name": "notification-service",
        "logBody": {
            "@timestamp": "2024-11-18T04:09:08.937Z",
            "@version": "1",
            "message": "Get the notification template name UNSUCCESSFUL_ONBOARDING, for customer ebf642db-51c7-4b97-822d-40e83e60386a",
            "logger_name": "com.arbm.digibank.service.NotificationTemplateService",
            "thread_name": "org.springframework.kafka.KafkaListenerEndpointContainer#0-0-C-1",
            "level": "INFO",
            "level_value": 20000,
            "springAppName": "notification-service",
            "traceId": "673abddf6d8ebe0b919b7954347a9863",
            "spanId": "89cc9fe0b9314e02",
            "bc": "shared"
        }
    }
]